disruptive/__init__.py
disruptive/authentication.py
disruptive/errors.py
disruptive/logging.py
disruptive/outputs.py
disruptive/py.typed
disruptive/requests.py
disruptive/transforms.py
disruptive/events/__init__.py
disruptive/events/events.py
disruptive/resources/__init__.py
disruptive/resources/claim.py
disruptive/resources/data_connector.py
disruptive/resources/device.py
disruptive/resources/emulator.py
disruptive/resources/eventhistory.py
disruptive/resources/organization.py
disruptive/resources/project.py
disruptive/resources/role.py
disruptive/resources/service_account.py
disruptive/resources/stream.py
disruptive-1.7.3.dist-info/LICENSE
disruptive-1.7.3.dist-info/METADATA
disruptive-1.7.3.dist-info/WHEEL
disruptive-1.7.3.dist-info/top_level.txt
disruptive-1.7.3.dist-info/RECORD
