Metadata-Version: 2.2
Name: disruptive
Version: 1.7.3
Summary: Disruptive Technologies Python API.
Home-page: https://github.com/disruptive-technologies/disruptive-python
Author: Disruptive Technologies Research AS
Author-email: developer-support@disruptive-technologies.com
Project-URL: Documentation, https://developer.disruptive-technologies.com/api/libraries/python/
Project-URL: Developers Page, https://developer.disruptive-technologies.com/docs/
Keywords: disruptive,technologies,dt,rest,api
Classifier: Natural Language :: English
Classifier: License :: OSI Approved :: MIT License
Classifier: Development Status :: 5 - Production/Stable
Classifier: Intended Audience :: Developers
Classifier: Programming Language :: Python :: 3.9
Classifier: Programming Language :: Python :: 3.10
Classifier: Programming Language :: Python :: 3.11
Classifier: Programming Language :: Python :: 3.12
Classifier: Programming Language :: Python :: 3.13
Classifier: Operating System :: OS Independent
Requires-Python: >=3.9
License-File: LICENSE
Requires-Dist: requests<3.0.0,>=2.19.0
Provides-Extra: dev
Requires-Dist: setuptools>=75.1.0; extra == "dev"
Requires-Dist: wheel>=0.44.0; extra == "dev"
Requires-Dist: pytest>=8.3.3; extra == "dev"
Requires-Dist: pytest-mock>=3.14.0; extra == "dev"
Requires-Dist: pytest-cov>=5.0.0; extra == "dev"
Requires-Dist: mypy>=1.11.2; extra == "dev"
Requires-Dist: flake8>=7.1.1; extra == "dev"
Provides-Extra: extra
Requires-Dist: pandas<3.0.0,>=2.0.0; extra == "extra"
Requires-Dist: polars<2.0.0,>=1.0.0; extra == "extra"
